setup.py
ozelot/__init__.py
ozelot/cache.py
ozelot/client.py
ozelot/config.py
ozelot.egg-info/PKG-INFO
ozelot.egg-info/SOURCES.txt
ozelot.egg-info/dependency_links.txt
ozelot.egg-info/not-zip-safe
ozelot.egg-info/requires.txt
ozelot.egg-info/top_level.txt
ozelot/etl/__init__.py
ozelot/etl/targets.py
ozelot/etl/tasks.py
ozelot/etl/util.py
ozelot/orm/__init__.py
ozelot/orm/base.py
ozelot/orm/target.py