Metadata-Version: 1.1
Name: ozelot
Version: 0.2.4
Summary: A package for building maintanable ETL pipelines
Home-page: https://github.com/trycs/ozelot
Author: Eberhard Hansis
Author-email: contact@transparent-analytics.de
License: MIT
Keywords: data analytics ETL
Platform: UNKNOWN
Classifier: Development Status :: 3 - Alpha
Classifier: License :: OSI Approved :: MIT License
Classifier: Programming Language :: Python :: 2.7
Classifier: Programming Language :: Python :: 3.5
Classifier: Topic :: Scientific/Engineering :: Information Analysis
